PE/pe.v
`timescale 1ns / 1ps

module PE_unit #(
    parameter DATA_WIDTH = 16, // As per paper's precision
    parameter ACCUM_WIDTH = 32 // Accumulator width to prevent overflow
) (
    input wire                      clk,
    input wire                      rst_n,
    input wire [1:0]                dataflow_sel, // 00: WS, 01: IS, 10: OS

    // Data Inputs
    input wire                      preload_en,   // preload data enable
    input wire [DATA_WIDTH-1:0]     preload_data, // preload data
    input wire [DATA_WIDTH-1:0]     input_0,      
    input wire [ACCUM_WIDTH-1:0]    input_1,      
    input wire [DATA_WIDTH-1:0]     input_2,     

    // Data Outputs
    output wire [DATA_WIDTH-1:0]    output_0,     
    output wire [ACCUM_WIDTH-1:0]   output_1,     
    output wire [DATA_WIDTH-1:0]    output_2    
);

    localparam WS_MODE = 2'b00;
    localparam IS_MODE = 2'b01;
    localparam OS_MODE = 2'b10;

    reg [DATA_WIDTH-1:0]   local_buffer; // Stores stationary data
    reg [ACCUM_WIDTH-1:0]  accumulator;  // accumulator for the MAC unit

    wire [DATA_WIDTH-1:0]  multiplier_in_A;
    wire [DATA_WIDTH-1:0]  multiplier_in_B;
    wire [ACCUM_WIDTH-1:0] adder_in_B;
    wire [ACCUM_WIDTH-1:0] mac_result;

    // Registered outputs for pipelining
    reg [DATA_WIDTH-1:0]   output_0_reg;
    reg [ACCUM_WIDTH-1:0]  output_1_reg;
    reg [DATA_WIDTH-1:0]   output_2_reg;

    // MUX for Multiplier (preload or input_0)
    assign multiplier_in_A = (dataflow_sel == OS_MODE)? input_0 : local_buffer;

    assign multiplier_in_B = input_2;

    // Mux for Adder (accumulator or input_1)
    assign adder_in_B = (dataflow_sel == OS_MODE)? accumulator : input_1;

    // mac_result = (A * B) + C
    assign mac_result = (multiplier_in_A * multiplier_in_B) + adder_in_B;

    always @(posedge clk or negedge rst_n) begin
        if (!rst_n) begin
            // Reset state
            local_buffer <= 0;
            accumulator  <= 0;
            output_0_reg <= 0;
            output_1_reg <= 0;
            output_2_reg <= 0;
        end else begin
            if (preload_en) begin
                local_buffer <= preload_data;
            end

            accumulator <= mac_result;

            case (dataflow_sel)
                WS_MODE: begin
                    output_0_reg <= 0; // Not used
                    output_1_reg <= mac_result; // PartialSum'
                    output_2_reg <= input_2;    // Input passes through
                end
                IS_MODE: begin
                    output_0_reg <= 0; // Not used
                    output_1_reg <= mac_result; // PartialSum'
                    output_2_reg <= input_2;    // Weight passes through
                end
                OS_MODE: begin
                    output_0_reg <= input_0;    // Weight passes through
                    output_1_reg <= 0; // Not used, result is stationary
                    output_2_reg <= input_2;    // Input passes through
                end
                default: begin
                    output_0_reg <= 0;
                    output_1_reg <= 0;
                    output_2_reg <= 0;
                end
            endcase
        end
    end

    assign output_0 = output_0_reg;
    assign output_1 = output_1_reg;
    assign output_2 = output_2_reg;

endmodule

PE/pe_tb.v
`timescale 1ns / 1ps

module pe_tb();

    parameter DATA_WIDTH = 16;
    parameter ACCUM_WIDTH = 32;
    parameter CLK_PERIOD = 10;

    reg                      clk;
    reg                      rst_n;
    reg [1:0]                dataflow_sel;
    reg                      preload_en;
    reg [DATA_WIDTH-1:0]     preload_data;
    reg [DATA_WIDTH-1:0]     input_0;
    reg [DATA_WIDTH-1:0]     input_1;
    reg [DATA_WIDTH-1:0]     input_2;

    wire [DATA_WIDTH-1:0]    output_0;
    wire [ACCUM_WIDTH-1:0]   output_1;
    wire [DATA_WIDTH-1:0]    output_2;

    localparam WS_MODE = 2'b00;
    localparam IS_MODE = 2'b01;
    localparam OS_MODE = 2'b10;

    PE_unit #(
        .DATA_WIDTH(DATA_WIDTH),
        .ACCUM_WIDTH(ACCUM_WIDTH)
    ) uut (
        .clk(clk),
        .rst_n(rst_n),
        .dataflow_sel(dataflow_sel),
        .preload_en(preload_en),
        .preload_data(preload_data),
        .input_0(input_0),
        .input_1(input_1),
        .input_2(input_2),
        .output_0(output_0),
        .output_1(output_1),
        .output_2(output_2)
    );

    always #(CLK_PERIOD/2) clk = ~clk;

    initial begin
        $dumpfile("pe_tb.vcd");
        $dumpvars(0, pe_tb);
        
        $display("=== PE Unit Testbench Started ===");
        
        clk = 0;
        rst_n = 0;
        dataflow_sel = 2'b00;
        preload_en = 0;
        preload_data = 0;
        input_0 = 0;
        input_1 = 0;
        input_2 = 0;
        
        #(CLK_PERIOD * 2);
        
        test_reset();
        test_preload();
        test_ws_mode();
        test_is_mode();
        test_os_mode();
        test_mac_operations();
        
        $display("=== All Tests Completed ===");
        $finish;
    end

    task test_reset();
        begin
            $display("\n--- Testing Reset Functionality ---");
            rst_n = 0;
            #(CLK_PERIOD);
            
            if (output_0 == 0 && output_1 == 0 && output_2 == 0) begin
                $display("PASS: Reset test - All outputs are 0");
            end else begin
                $display("FAIL: Reset test - Expected all outputs = 0, got output_0=%d, output_1=%d, output_2=%d", 
                        output_0, output_1, output_2);
            end
            
            rst_n = 1;
            #(CLK_PERIOD);
        end
    endtask

    task test_preload();
        begin
            $display("\n--- Testing Preload Functionality ---");
            rst_n = 1;
            dataflow_sel = WS_MODE;
            preload_en = 1;
            preload_data = 16'h1234;
            
            #(CLK_PERIOD);
            preload_en = 0;
            
            input_2 = 16'h0002;
            input_1 = 16'h0000;
            
            #(CLK_PERIOD);
            
            if (output_1 == (16'h1234 * 16'h0002)) begin
                $display("PASS: Preload test - Local buffer correctly loaded and used in MAC");
            end else begin
                $display("FAIL: Preload test - Expected %d, got %d", 
                        (16'h1234 * 16'h0002), output_1);
            end
        end
    endtask

    task test_ws_mode();
        begin
            $display("\n--- Testing Weight Stationary Mode ---");
            rst_n = 0;
            #(CLK_PERIOD);
            rst_n = 1;
            
            dataflow_sel = WS_MODE;
            preload_en = 1;
            preload_data = 16'h0005;
            #(CLK_PERIOD);
            preload_en = 0;
            
            input_0 = 16'h1111;
            input_1 = 16'h0010;
            input_2 = 16'h0003;
            
            #(CLK_PERIOD);
            
            $display("WS Mode Results:");
            $display("  output_0 = %d (expected: 0)", output_0);
            $display("  output_1 = %d (expected: %d)", output_1, (16'h0005 * 16'h0003 + 16'h0010));
            $display("  output_2 = %d (expected: %d)", output_2, 16'h0003);
            
            if (output_0 == 0 && 
                output_1 == (16'h0005 * 16'h0003 + 16'h0010) && 
                output_2 == 16'h0003) begin
                $display("PASS: WS Mode test");
            end else begin
                $display("FAIL: WS Mode test");
            end
        end
    endtask

    task test_is_mode();
        begin
            $display("\n--- Testing Input Stationary Mode ---");
            rst_n = 0;
            #(CLK_PERIOD);
            rst_n = 1;
            
            dataflow_sel = IS_MODE;
            preload_en = 1;
            preload_data = 16'h0007;
            #(CLK_PERIOD);
            preload_en = 0;
            
            input_0 = 16'h2222;
            input_1 = 16'h0020;
            input_2 = 16'h0004;
            
            #(CLK_PERIOD);
            
            $display("IS Mode Results:");
            $display("  output_0 = %d (expected: 0)", output_0);
            $display("  output_1 = %d (expected: %d)", output_1, (16'h0007 * 16'h0004 + 16'h0020));
            $display("  output_2 = %d (expected: %d)", output_2, 16'h0004);
            
            if (output_0 == 0 && 
                output_1 == (16'h0007 * 16'h0004 + 16'h0020) && 
                output_2 == 16'h0004) begin
                $display("PASS: IS Mode test");
            end else begin
                $display("FAIL: IS Mode test");
            end
        end
    endtask

    task test_os_mode();
        begin
            $display("\n--- Testing Output Stationary Mode ---");
            rst_n = 0;
            #(CLK_PERIOD);
            rst_n = 1;
            
            dataflow_sel = OS_MODE;
            preload_en = 1;
            preload_data = 16'h0009;
            #(CLK_PERIOD);
            preload_en = 0;
            
            input_0 = 16'h0006;
            input_1 = 16'h0030;
            input_2 = 16'h0005;
            
            #(CLK_PERIOD);
            
            $display("OS Mode Results (Cycle 1):");
            $display("  output_0 = %d (expected: %d)", output_0, 16'h0006);
            $display("  output_1 = %d (expected: 0)", output_1);
            $display("  output_2 = %d (expected: %d)", output_2, 16'h0005);
            
            input_0 = 16'h0008;
            input_2 = 16'h0003;
            #(CLK_PERIOD);
            
            $display("OS Mode Results (Cycle 2 - Accumulation):");
            $display("  output_0 = %d (expected: %d)", output_0, 16'h0008);
            $display("  output_2 = %d (expected: %d)", output_2, 16'h0003);
            
            if (output_0 == 16'h0008 && output_1 == 0 && output_2 == 16'h0003) begin
                $display("PASS: OS Mode test");
            end else begin
                $display("FAIL: OS Mode test");
            end
        end
    endtask

    task test_mac_operations();
        begin
            $display("\n--- Testing MAC Operations ---");
            rst_n = 0;
            #(CLK_PERIOD);
            rst_n = 1;
            
            dataflow_sel = WS_MODE;
            preload_en = 1;
            preload_data = 16'd10;
            #(CLK_PERIOD);
            preload_en = 0;
            
            input_1 = 32'd100;
            input_2 = 16'd5;
            #(CLK_PERIOD);
            
            $display("MAC Test: (10 * 5) + 100 = %d (expected: 150)", output_1);
            
            if (output_1 == 150) begin
                $display("PASS: MAC operation test");
            end else begin
                $display("FAIL: MAC operation test - Expected 150, got %d", output_1);
            end
            
            input_1 = 32'd200;
            input_2 = 16'd3;
            #(CLK_PERIOD);
            
            $display("MAC Test: (10 * 3) + 200 = %d (expected: 230)", output_1);
            
            if (output_1 == 230) begin
                $display("PASS: Second MAC operation test");
            end else begin
                $display("FAIL: Second MAC operation test - Expected 230, got %d", output_1);
            end
        end
    endtask

endmodule

PE/pe_tb.vcd
$date
	Fri Sep 26 12:06:36 2025
$end
$version
	Icarus Verilog
$end
$timescale
	1ps
$end
$scope module pe_tb $end
$var wire 16 ! output_2 [15:0] $end
$var wire 32 " output_1 [31:0] $end
$var wire 16 # output_0 [15:0] $end
$var parameter 32 $ ACCUM_WIDTH $end
$var parameter 32 % CLK_PERIOD $end
$var parameter 32 & DATA_WIDTH $end
$var parameter 2 ' IS_MODE $end
$var parameter 2 ( OS_MODE $end
$var parameter 2 ) WS_MODE $end
$var reg 1 * clk $end
$var reg 2 + dataflow_sel [1:0] $end
$var reg 16 , input_0 [15:0] $end
$var reg 16 - input_1 [15:0] $end
$var reg 16 . input_2 [15:0] $end
$var reg 16 / preload_data [15:0] $end
$var reg 1 0 preload_en $end
$var reg 1 1 rst_n $end
$scope module uut $end
$var wire 1 * clk $end
$var wire 2 2 dataflow_sel [1:0] $end
$var wire 16 3 input_0 [15:0] $end
$var wire 32 4 input_1 [31:0] $end
$var wire 16 5 input_2 [15:0] $end
$var wire 16 6 multiplier_in_B [15:0] $end
$var wire 16 7 output_0 [15:0] $end
$var wire 32 8 output_1 [31:0] $end
$var wire 16 9 output_2 [15:0] $end
$var wire 16 : preload_data [15:0] $end
$var wire 1 0 preload_en $end
$var wire 1 1 rst_n $end
$var wire 16 ; multiplier_in_A [15:0] $end
$var wire 32 < mac_result [31:0] $end
$var wire 32 = adder_in_B [31:0] $end
$var parameter 32 > ACCUM_WIDTH $end
$var parameter 32 ? DATA_WIDTH $end
$var parameter 2 @ IS_MODE $end
$var parameter 2 A OS_MODE $end
$var parameter 2 B WS_MODE $end
$var reg 32 C accumulator [31:0] $end
$var reg 16 D local_buffer [15:0] $end
$var reg 16 E output_0_reg [15:0] $end
$var reg 32 F output_1_reg [31:0] $end
$var reg 16 G output_2_reg [15:0] $end
$upscope $end
$scope task test_is_mode $end
$upscope $end
$scope task test_mac_operations $end
$upscope $end
$scope task test_os_mode $end
$upscope $end
$scope task test_preload $end
$upscope $end
$scope task test_reset $end
$upscope $end
$scope task test_ws_mode $end
$upscope $end
$upscope $end
$enddefinitions $end
$comment Show the parameter values. $end
$dumpall
b0 B
b10 A
b1 @
b10000 ?
b100000 >
b0 )
b10 (
b1 '
b10000 &
b1010 %
b100000 $
$end
#0
$dumpvars
b0 G
b0 F
b0 E
b0 D
b0 C
b0 =
b0 <
b0 ;
b0 :
b0 9
b0 8
b0 7
b0 6
b0 5
b0 4
b0 3
b0 2
01
00
b0 /
b0 .
b0 -
b0 ,
b0 +
0*
b0 #
b0 "
b0 !
$end
#5000
1*
#10000
0*
#15000
1*
#20000
0*
#25000
1*
#30000
0*
11
#35000
1*
#40000
0*
b1001000110100 /
b1001000110100 :
10
#45000
b1001000110100 ;
b1001000110100 D
1*
#50000
0*
b10010001101000 <
b10 6
b10 .
b10 5
00
#55000
b10 !
b10 9
b10 G
b10010001101000 "
b10010001101000 8
b10010001101000 F
b10010001101000 C
1*
#60000
b0 <
b0 ;
b0 !
b0 9
b0 G
b0 "
b0 8
b0 F
b0 C
b0 D
0*
01
#65000
1*
#70000
0*
b101 /
b101 :
10
11
#75000
b1010 <
b101 ;
b10 !
b10 9
b10 G
b101 D
1*
#80000
b10000 =
0*
b11111 <
b11 6
b11 .
b11 5
b10000 4
b10000 -
b1000100010001 ,
b1000100010001 3
00
#85000
b11 !
b11 9
b11 G
b11111 "
b11111 8
b11111 F
b11111 C
1*
#90000
b10000 <
b0 ;
b0 !
b0 9
b0 G
b0 "
b0 8
b0 F
b0 C
b0 D
0*
01
#95000
1*
#100000
0*
b111 /
b111 :
10
b1 +
b1 2
11
#105000
b100101 <
b111 ;
b11 !
b11 9
b11 G
b10000 "
b10000 8
b10000 F
b10000 C
b111 D
1*
#110000
b100000 =
0*
b111100 <
b100 6
b100 .
b100 5
b100000 4
b100000 -
b10001000100010 ,
b10001000100010 3
00
#115000
b100 !
b100 9
b100 G
b111100 "
b111100 8
b111100 F
b111100 C
1*
#120000
b100000 <
b0 ;
b0 !
b0 9
b0 G
b0 "
b0 8
b0 F
b0 C
b0 D
0*
01
#125000
1*
#130000
b10001000100010 ;
b1000100010001000 <
b0 =
0*
b1001 /
b1001 :
10
b10 +
b10 2
11
#135000
b10001000100010000 <
b1000100010001000 =
b100 !
b100 9
b100 G
b10001000100010 #
b10001000100010 7
b10001000100010 E
b1000100010001000 C
b1001 D
1*
#140000
b110 ;
0*
b1000100010100110 <
b101 6
b101 .
b101 5
b110000 4
b110000 -
b110 ,
b110 3
00
#145000
b1000100011000100 <
b1000100010100110 =
b101 !
b101 9
b101 G
b110 #
b110 7
b110 E
b1000100010100110 C
1*
#150000
b1000 ;
0*
b1000100010111110 <
b11 6
b11 .
b11 5
b1000 ,
b1000 3
#155000
b1000100011010110 <
b1000100010111110 =
b11 !
b11 9
b11 G
b1000 #
b1000 7
b1000 E
b1000100010111110 C
1*
#160000
b11000 <
b0 =
b0 !
b0 9
b0 G
b0 #
b0 7
b0 E
b0 C
b0 D
0*
01
#165000
1*
#170000
b0 ;
b110000 <
b110000 =
0*
b1010 /
b1010 :
10
b0 +
b0 2
11
#175000
b1001110 <
b1010 ;
b11 !
b11 9
b11 G
b110000 "
b110000 8
b110000 F
b110000 C
b1010 D
1*
#180000
b1100100 =
0*
b10010110 <
b101 6
b101 .
b101 5
b1100100 4
b1100100 -
00
#185000
b101 !
b101 9
b101 G
b10010110 "
b10010110 8
b10010110 F
b10010110 C
1*
#190000
b11001000 =
0*
b11100110 <
b11 6
b11 .
b11 5
b11001000 4
b11001000 -
#195000
b11 !
b11 9
b11 G
b11100110 "
b11100110 8
b11100110 F
b11100110 C
1*
